application_example/__init__.py
application_example/example.py
kctest_francesc-0.0.1.dist-info/METADATA
kctest_francesc-0.0.1.dist-info/WHEEL
kctest_francesc-0.0.1.dist-info/top_level.txt
kctest_francesc-0.0.1.dist-info/RECORD
