Metadata-Version: 2.1
Name: kctest-francesc
Version: 0.0.1
Summary: Aplicación de ejemplo
Author: keepcoder
Author-email: kcpypitest@gmail.com
License: UNKNOWN
Platform: UNKNOWN
Requires-Python: >=3.9
Requires-Dist: build
Requires-Dist: twine
Requires-Dist: coloredlogs
